pyavia/__init__.py
pyavia/containers.py
pyavia/fortran.py
pyavia/iter.py
pyavia/math.py
pyavia/types.py
pyavia/units.py
pyavia/util.py
pyavia/aero/__init__.py
pyavia/aero/atmosphere.py
pyavia/aero/gas.py
pyavia/aero/imperfect_gas.py
pyavia/aero/perfect_gas.py
pyavia/data/__init__.py
pyavia/data/filter.py
pyavia/data/interpolate.py
pyavia/geo/__init__.py
pyavia/geo/bezier.py
pyavia/geo/common.py
pyavia/geo/spacing.py
pyavia/prop/__init__.py
pyavia/solve/__init__.py
pyavia/solve/bisect_root.py
pyavia/solve/dqnm.py
pyavia/solve/fixed_point.py
pyavia/solve/inverse.py
pyavia/solve/newton_bounded.py
pyavia/struct/__init__.py
pyavia/struct/kt_hole3d.py
pyavia/struct/sn_life.py
pyavia/struct/stress.py
pyavia-0.0.3.dist-info/LICENSE
pyavia-0.0.3.dist-info/METADATA
pyavia-0.0.3.dist-info/WHEEL
pyavia-0.0.3.dist-info/top_level.txt
pyavia-0.0.3.dist-info/RECORD
