Metadata-Version: 2.1
Name: pyavia
Version: 0.0.3
Summary: Useful functions commonly used in aerospace engineering.
Home-page: https://github.com/ericjwhitney/pyavia
Author: Eric J. Whitney
Author-email: eric.j.whitney@optusnet.removethispart.com.au
License: UNKNOWN
Keywords: aerospace engineering tools
Platform: UNKNOWN
Classifier: Development Status :: 2 - Pre-Alpha
Classifier: Intended Audience :: Science/Research
Classifier: License :: OSI Approved :: MIT License
Classifier: Natural Language :: English
Classifier: Operating System :: OS Independent
Classifier: Programming Language :: Python :: 3.9
Classifier: Topic :: Scientific/Engineering
Requires-Python: >=3.9
License-File: LICENSE
Requires-Dist: numpy
Requires-Dist: scipy
